i2clcd/__init__.py
i2clcd-0.0.1.dist-info/LICENSE
i2clcd-0.0.1.dist-info/METADATA
i2clcd-0.0.1.dist-info/WHEEL
i2clcd-0.0.1.dist-info/top_level.txt
i2clcd-0.0.1.dist-info/RECORD
