Metadata-Version: 2.1
Name: i2clcd
Version: 0.0.1
Summary: driver for LCD1602/2002/2004 with I2C adapter, for Raspberry Pi or other device
Home-page: https://github.com/WuSiYu/python-i2clcd
Author: SiYu Wu
Author-email: wu.siyu@hotmail.com
License: UNKNOWN
Platform: UNKNOWN
Classifier: Development Status :: 3 - Alpha
Classifier: Programming Language :: Python :: 3 :: Only
Classifier: License :: OSI Approved :: MIT License
